[
    {
        "nombre": "Roberto",
        "apellido": "Gonzales",
        "dni": 44480358,
        "email":"benjaeceiza400@gmail.com",
        "telefono":2657310116,
        "id":1,
        "imagen":"/src/assets/usuario.png",
        "direccion":"Avenida Mitre"
    },
    {
        "nombre": "Ramón",
        "apellido": "Diaz",
        "dni": 44480536,
        "email":"gonzasilvani@gmail.com",
        "telefono":26571212121,
        "id":2,
        "imagen":"/src/assets/usuario.png",
        "direccion":"belgrano 486"
        
    },
    {
        "nombre": "Norma",
        "apellido": "Perez",
        "dni": 343432432,
        "email":"cesarsilvani@gmail.com",
        "telefono":265734346,
        "id":3,
        "imagen":"/src/assets/usuario.png",
        "direccion":"La Ribera"
    }
   
]